tktooltip/__init__.py
tktooltip/_version.py
tktooltip/tooltip.py
tktooltip/version.py
tkinter_tooltip-3.1.2.dist-info/LICENSE
tkinter_tooltip-3.1.2.dist-info/METADATA
tkinter_tooltip-3.1.2.dist-info/WHEEL
tkinter_tooltip-3.1.2.dist-info/top_level.txt
tkinter_tooltip-3.1.2.dist-info/RECORD
